zviz/__init__.py
zviz/nxgraph.py
zviz/tree.py
zviz/zviz.py
zviz/utils/__init__.py
zviz/utils/project_util.py
zviz/utils/util.py
zviz-1.0.4.dist-info/METADATA
zviz-1.0.4.dist-info/WHEEL
zviz-1.0.4.dist-info/top_level.txt
zviz-1.0.4.dist-info/RECORD
