Metadata-Version: 2.1
Name: zviz
Version: 1.0.4
Summary: Visualize the progress of your torch.
Home-page: https://github.com/hokuseihal/torchzviz
Author: hokuseihal
Author-email: hokuseihal@gmail.com
License: MIT
Keywords: zviz
Platform: UNKNOWN
Classifier: License :: OSI Approved :: MIT License
Classifier: Programming Language :: Python :: 3.7
Requires-Dist: networkx
Requires-Dist: pygraphviz
